peptide_mapper/mapper.py
peptide_mapper/version.txt
peptide_mapper-0.4.3.dist-info/LICENSE
peptide_mapper-0.4.3.dist-info/METADATA
peptide_mapper-0.4.3.dist-info/WHEEL
peptide_mapper-0.4.3.dist-info/top_level.txt
peptide_mapper-0.4.3.dist-info/RECORD
