Metadata-Version: 2.1
Name: peptide-mapper
Version: 0.4.3
Summary: Peptide mapper
Home-page: http://pymzml.github.com
Author: 
Author-email: christian@fufezan.net
License: The MIT license
Platform: any that supports python 3.7
Classifier: Development Status :: 4 - Beta
Classifier: Environment :: Console
Classifier: Intended Audience :: Education
Classifier: Intended Audience :: Science/Research
Classifier: Intended Audience :: Developers
Classifier: License :: OSI Approved :: MIT License
Classifier: Operating System :: MacOS :: MacOS X
Classifier: Operating System :: Microsoft :: Windows
Classifier: Operating System :: POSIX
Classifier: Operating System :: POSIX :: SunOS/Solaris
Classifier: Operating System :: Unix
Classifier: Programming Language :: Python :: 3.5
Classifier: Topic :: Scientific/Engineering :: Bio-Informatics
Classifier: Topic :: Scientific/Engineering :: Chemistry
Classifier: Topic :: Scientific/Engineering :: Medical Science Apps.
Requires-Python: >=3.7.0
License-File: LICENSE
Requires-Dist: pytest
Requires-Dist: pyahocorasick
